{"name":"Digiligenciamiento exitoso del formulario Popup Validation","id":"formulario-popup-validation;digiligenciamiento-exitoso-del-formulario-popup-validation","testSteps":[{"number":1,"description":"Given Autentico en colorlib con usuario \"demo\" y clave \"demo\"","duration":4870,"startTime":"2022-11-09T11:45:13.234317300-05:00[America/Bogota]","screenshots":[{"screenshot":"c37e1cb0e2de287da47038eec75cff5b96750129e7f173a24536700c6a509922.png"}],"result":"SUCCESS","precondition":false,"children":[{"number":2,"description":"Pablo opens the Color lib page","duration":2006,"startTime":"2022-11-09T11:45:13.548897300-05:00[America/Bogota]","screenshots":[{"screenshot":"7bc65727466308220a0ece1c5b8f2bb315a322c626adf0328b48b3a535037f27.png"}],"result":"SUCCESS","precondition":false},{"number":3,"description":"Pablo enters \u0027demo\u0027 into Campo para ingresar el username","duration":468,"startTime":"2022-11-09T11:45:15.602206-05:00[America/Bogota]","screenshots":[{"screenshot":"08abe9e0cdb7b41599d20e2c6197cab023c729b6bfc6985c7be57d708ce002c2.png"}],"result":"SUCCESS","precondition":false},{"number":4,"description":"Pablo enters \u0027demo\u0027 into Campo para ingresar el passwword","duration":363,"startTime":"2022-11-09T11:45:16.077616900-05:00[America/Bogota]","screenshots":[{"screenshot":"d2ef19a7fef3f43d659066a62a474cfdea9569585299a909d133fa83c018ebc2.png"}],"result":"SUCCESS","precondition":false},{"number":5,"description":"Pablo clicks on Botón de login","duration":1293,"startTime":"2022-11-09T11:45:16.445762300-05:00[America/Bogota]","screenshots":[{"screenshot":"c37e1cb0e2de287da47038eec75cff5b96750129e7f173a24536700c6a509922.png"}],"result":"SUCCESS","precondition":false},{"number":6,"description":"Then validar","duration":181,"startTime":"2022-11-09T11:45:17.807529300-05:00[America/Bogota]","screenshots":[{"screenshot":"c37e1cb0e2de287da47038eec75cff5b96750129e7f173a24536700c6a509922.png"}],"result":"SUCCESS","precondition":false}]},{"number":7,"description":"And Ingreso a la funcionalidad Forms Validation","duration":1150,"startTime":"2022-11-09T11:45:18.105079800-05:00[America/Bogota]","screenshots":[{"screenshot":"596a8acdee4fbd19db31aee87cab9aef2c8f86d24d495ed1470609823fea4753.png"}],"result":"SUCCESS","precondition":false,"children":[{"number":8,"description":"Pablo clicks on Label menú FORMS","duration":222,"startTime":"2022-11-09T11:45:18.120705800-05:00[America/Bogota]","screenshots":[{"screenshot":"523b28eaf27fd628a08bc5a03b45ff3ed598dfff2cdfeeec0a5c2bc23fb80c39.png"}],"result":"SUCCESS","precondition":false},{"number":9,"description":"Pablo clicks on Label submenú FORMS VALIDATIONS","duration":618,"startTime":"2022-11-09T11:45:18.345729600-05:00[America/Bogota]","screenshots":[{"screenshot":"596a8acdee4fbd19db31aee87cab9aef2c8f86d24d495ed1470609823fea4753.png"}],"result":"SUCCESS","precondition":false},{"number":10,"description":"Then Valor del Label Titulo Ventana Form Validation should be \u0027Popup Validation\u0027","duration":185,"startTime":"2022-11-09T11:45:18.969650500-05:00[America/Bogota]","screenshots":[{"screenshot":"596a8acdee4fbd19db31aee87cab9aef2c8f86d24d495ed1470609823fea4753.png"}],"result":"SUCCESS","precondition":false}]},{"number":11,"description":"When Diligencio Formulario Popup Validation\r\n| strRequired | strSelect | strMultipleSelect | strMultipleSelect2 | strUrl | strEmail | strPassword | strConfirmPassword | strMinimumFieldSize | strMaximumFieldSize | strNumber | strIP | strDate | strDateEarlier |\r\n| a | Tennis | Tennis | Golf | http://tenis.com | tenis@tenis.com | 123 | 123 | 123456 | 123456 | 123 | 192.168.3.1 | 2011-12-01 | 2011-12-01 |","duration":4853,"startTime":"2022-11-09T11:45:19.256858-05:00[America/Bogota]","screenshots":[{"screenshot":"596a8acdee4fbd19db31aee87cab9aef2c8f86d24d495ed1470609823fea4753.png"}],"result":"SUCCESS","precondition":false,"children":[{"number":12,"description":"Pablo enters \u0027a\u0027 into Input para el campo Required","duration":295,"startTime":"2022-11-09T11:45:19.296622800-05:00[America/Bogota]","screenshots":[{"screenshot":"8d5fd3925b559e0e8a888223cadd0e5e1dca81a363900c0f95736393d7eab416.png"}],"result":"SUCCESS","precondition":false},{"number":13,"description":"Pablo select Tennis on Select para seleccionar deporte","duration":270,"startTime":"2022-11-09T11:45:19.594018100-05:00[America/Bogota]","screenshots":[{"screenshot":"14e01ffbae599eae0b55aae7db1e8c22a6c31ab48e5853684e11ab9646fcc298.png"}],"result":"SUCCESS","precondition":false},{"number":14,"description":"Pablo select Tennis on Select para seleccionar segundo deporte","duration":262,"startTime":"2022-11-09T11:45:19.865671700-05:00[America/Bogota]","screenshots":[{"screenshot":"d8cf3955358f1c22f73eac11f84de27df1d32381f28b1e09d757c34628b89f84.png"}],"result":"SUCCESS","precondition":false},{"number":15,"description":"Pablo select Golf on Select para seleccionar segundo deporte","duration":249,"startTime":"2022-11-09T11:45:20.130304300-05:00[America/Bogota]","screenshots":[{"screenshot":"9259e1986658c5ff904e9d4c69be167befab629cf6b35c9d70390a2be63ed9d7.png"}],"result":"SUCCESS","precondition":false},{"number":16,"description":"Pablo enters \u0027http://tenis.com\u0027 into Input para el campo URL","duration":304,"startTime":"2022-11-09T11:45:20.382892-05:00[America/Bogota]","screenshots":[{"screenshot":"29b3e22322b71c3ad3a2380bc3c392c08f4ba6ef161476ff6850ca91ca0ff009.png"}],"result":"SUCCESS","precondition":false},{"number":17,"description":"Pablo enters \u0027tenis@tenis.com\u0027 into Input para el campo E-MAIL","duration":312,"startTime":"2022-11-09T11:45:20.688796900-05:00[America/Bogota]","screenshots":[{"screenshot":"e26b372c7a10eac2a542ef5dacf05bcdfa0f9d697f0d11326f3118e4fa4ad55a.png"}],"result":"SUCCESS","precondition":false},{"number":18,"description":"Pablo enters \u0027123\u0027 into Input para el campo Password","duration":287,"startTime":"2022-11-09T11:45:21.002579400-05:00[America/Bogota]","screenshots":[{"screenshot":"15b9debbaaa480acc15892ef4af6879c6a48995edd1332c4e0a60bc1e8cb3713.png"}],"result":"SUCCESS","precondition":false},{"number":19,"description":"Pablo enters \u0027123\u0027 into Input para el campo Confirm Password","duration":276,"startTime":"2022-11-09T11:45:21.292143200-05:00[America/Bogota]","screenshots":[{"screenshot":"b51730d659b5c521624672db42c97797a092cc33f08919dba39926338306b341.png"}],"result":"SUCCESS","precondition":false},{"number":20,"description":"Pablo enters \u0027123456\u0027 into Input para el campo MINIMUN FIELD SIZE","duration":286,"startTime":"2022-11-09T11:45:21.569664100-05:00[America/Bogota]","screenshots":[{"screenshot":"da0ab7bdd475fcd73710f3e0e69d97889e50035ce4659c0d86a63178ada37d7f.png"}],"result":"SUCCESS","precondition":false},{"number":21,"description":"Pablo enters \u0027123456\u0027 into Input para el campo MAXIMUN FIELD SIZE","duration":270,"startTime":"2022-11-09T11:45:21.856262300-05:00[America/Bogota]","screenshots":[{"screenshot":"a59356b7bb8e7c3ac104a2e2edf12a7cd565cbd6c2a26b76a4e58979670064c7.png"}],"result":"SUCCESS","precondition":false},{"number":22,"description":"Pablo enters \u0027123\u0027 into Input para el campo NUMBER","duration":304,"startTime":"2022-11-09T11:45:22.128670800-05:00[America/Bogota]","screenshots":[{"screenshot":"9172ee9cdf79fef4293b56fc81259f006f30dc4a671629eaa0dfc59d6762b48d.png"}],"result":"SUCCESS","precondition":false},{"number":23,"description":"Pablo enters \u0027192.168.3.1\u0027 into Input para el campo IP","duration":304,"startTime":"2022-11-09T11:45:22.435070400-05:00[America/Bogota]","screenshots":[{"screenshot":"14b053f3f433e5f811de06f113b722a6de5052ff18e54670ef06ed1ec9aafd23.png"}],"result":"SUCCESS","precondition":false},{"number":24,"description":"Pablo enters \u00272011-12-01\u0027 into Input para el campo DATE","duration":283,"startTime":"2022-11-09T11:45:22.739189200-05:00[America/Bogota]","screenshots":[{"screenshot":"79602ac20e27d5af6ee08c284628213d63d071b562f6010eeb5e6fb41e3e30f5.png"}],"result":"SUCCESS","precondition":false},{"number":25,"description":"Pablo enters \u00272011-12-01\u0027 into Input para el campo DATE EARLIER","duration":282,"startTime":"2022-11-09T11:45:23.024676800-05:00[America/Bogota]","screenshots":[{"screenshot":"8af7572005901e68eb3485cc659bece09e6669dbae92350c91db08f552876c61.png"}],"result":"SUCCESS","precondition":false},{"number":26,"description":"Pablo clicks on Botón de VALIDATE","duration":637,"startTime":"2022-11-09T11:45:23.308315600-05:00[America/Bogota]","screenshots":[{"screenshot":"596a8acdee4fbd19db31aee87cab9aef2c8f86d24d495ed1470609823fea4753.png"}],"result":"SUCCESS","precondition":false}]},{"number":27,"description":"Then Verifico ingreso exitoso","duration":10358,"startTime":"2022-11-09T11:45:24.111359300-05:00[America/Bogota]","screenshots":[{"screenshot":"5f355c234100f9f9431f879f9db2c811d8e6109cd858ce19454f07bb4f4d3fa2.png"}],"result":"SUCCESS","precondition":false,"children":[{"number":28,"description":"Then Validar Exitencia de Popup should be (false)","duration":10265,"startTime":"2022-11-09T11:45:24.113363400-05:00[America/Bogota]","screenshots":[{"screenshot":"5f355c234100f9f9431f879f9db2c811d8e6109cd858ce19454f07bb4f4d3fa2.png"}],"result":"SUCCESS","precondition":false,"children":[{"number":29,"description":"Then Popup de validaci\u0026oacute;n sobre cada campo should be an element that is not visible","duration":10135,"startTime":"2022-11-09T11:45:24.138266-05:00[America/Bogota]","screenshots":[{"screenshot":"5f355c234100f9f9431f879f9db2c811d8e6109cd858ce19454f07bb4f4d3fa2.png"}],"result":"SUCCESS","precondition":false}]}]}],"userStory":{"id":"formulario-popup-validation","storyName":"Formulario Popup Validation","path":"src/test/resources/features/demo.feature","narrative":"  El usuario debe poder ingresar al formulario los datos requeridos.\n  Cada campo del formulario realiza validaciones de obligatoriedad,\n  longitud y formato, el sistema debe presentar las validaciones respectivas\n  para cada campo a través un globo informativo.","type":"feature"},"featureTag":{"name":"Features/Formulario Popup Validation","type":"feature"},"title":"Digiligenciamiento exitoso del formulario Popup Validation","description":"  no se presenta ningún mensaje de validación.","tags":[{"name":"Formulario popup validation","type":"feature"},{"name":"Regresion","type":"tag"},{"name":"CasoExitoso","type":"tag"}],"startTime":"2022-11-09T11:45:12.214422900-05:00[America/Bogota]","duration":22303,"projectKey":"","sessionId":"8e8048cca3110954aeac209814e0ebc7","driver":"chrome:pablo","manual":false,"testSource":"Cucumber","result":"SUCCESS"}