{"name":"Digiligenciamiento exitoso del formulario Popup Validation","id":"formulario-popup-validation;digiligenciamiento-exitoso-del-formulario-popup-validation","testSteps":[{"number":1,"description":"Given Autentico en colorlib con usuario \"demo\" y clave \"demo\"","duration":18877,"startTime":"2022-11-23T16:08:06.120626700-05:00[America/Bogota]","screenshots":[{"screenshot":"c37e1cb0e2de287da47038eec75cff5b96750129e7f173a24536700c6a509922.png"}],"result":"SUCCESS","precondition":false,"children":[{"number":2,"description":"Pablo opens the Color lib page","duration":2666,"startTime":"2022-11-23T16:08:06.633853-05:00[America/Bogota]","screenshots":[{"screenshot":"7bc65727466308220a0ece1c5b8f2bb315a322c626adf0328b48b3a535037f27.png"}],"result":"SUCCESS","precondition":false},{"number":3,"description":"Pablo enters \u0027demo\u0027 into Campo para ingresar el username","duration":536,"startTime":"2022-11-23T16:08:09.333297300-05:00[America/Bogota]","screenshots":[{"screenshot":"08abe9e0cdb7b41599d20e2c6197cab023c729b6bfc6985c7be57d708ce002c2.png"}],"result":"SUCCESS","precondition":false},{"number":4,"description":"Pablo enters \u0027demo\u0027 into Campo para ingresar el passwword","duration":474,"startTime":"2022-11-23T16:08:09.876079600-05:00[America/Bogota]","screenshots":[{"screenshot":"b6ce701175db4548e4a941ef9d78f926e55fe978a530105a2a08bca768b2903d.png"}],"result":"SUCCESS","precondition":false},{"number":5,"description":"Pablo clicks on Botón de login","duration":14158,"startTime":"2022-11-23T16:08:10.354196800-05:00[America/Bogota]","screenshots":[{"screenshot":"c37e1cb0e2de287da47038eec75cff5b96750129e7f173a24536700c6a509922.png"}],"result":"SUCCESS","precondition":false},{"number":6,"description":"Then validar","duration":239,"startTime":"2022-11-23T16:08:24.630788500-05:00[America/Bogota]","screenshots":[{"screenshot":"c37e1cb0e2de287da47038eec75cff5b96750129e7f173a24536700c6a509922.png"}],"result":"SUCCESS","precondition":false}]},{"number":7,"description":"And Ingreso a la funcionalidad Forms Validation","duration":1422,"startTime":"2022-11-23T16:08:24.999660-05:00[America/Bogota]","screenshots":[{"screenshot":"596a8acdee4fbd19db31aee87cab9aef2c8f86d24d495ed1470609823fea4753.png"}],"result":"SUCCESS","precondition":false,"children":[{"number":8,"description":"Pablo clicks on Label menú FORMS","duration":298,"startTime":"2022-11-23T16:08:25.019375600-05:00[America/Bogota]","screenshots":[{"screenshot":"28f11030b8c83b772185b98c234e28e9dd02e9f8074c16add083a3439864de7b.png"}],"result":"SUCCESS","precondition":false},{"number":9,"description":"Pablo clicks on Label submenú FORMS VALIDATIONS","duration":744,"startTime":"2022-11-23T16:08:25.322904300-05:00[America/Bogota]","screenshots":[{"screenshot":"596a8acdee4fbd19db31aee87cab9aef2c8f86d24d495ed1470609823fea4753.png"}],"result":"SUCCESS","precondition":false},{"number":10,"description":"Then Valor del Label Titulo Ventana Form Validation should be \u0027Popup Validation\u0027","duration":232,"startTime":"2022-11-23T16:08:26.076405400-05:00[America/Bogota]","screenshots":[{"screenshot":"596a8acdee4fbd19db31aee87cab9aef2c8f86d24d495ed1470609823fea4753.png"}],"result":"SUCCESS","precondition":false}]},{"number":11,"description":"When Diligencio Formulario Popup Validation\r\n| strRequired | strSelect | strMultipleSelect | strMultipleSelect2 | strUrl | strEmail | strPassword | strConfirmPassword | strMinimumFieldSize | strMaximumFieldSize | strNumber | strIP | strDate | strDateEarlier |\r\n| a | Tennis | Tennis | Golf | http://tenis.com | tenis@tenis.com | 123 | 123 | 123456 | 123456 | 123 | 192.168.3.1 | 2011-12-01 | 2011-12-01 |","duration":6023,"startTime":"2022-11-23T16:08:26.429278400-05:00[America/Bogota]","screenshots":[{"screenshot":"596a8acdee4fbd19db31aee87cab9aef2c8f86d24d495ed1470609823fea4753.png"}],"result":"SUCCESS","precondition":false,"children":[{"number":12,"description":"Pablo enters \u0027a\u0027 into Input para el campo Required","duration":346,"startTime":"2022-11-23T16:08:26.477203600-05:00[America/Bogota]","screenshots":[{"screenshot":"77c8aea249c71566ef18a1f3084ea574f4419fe393ea02daea7b0083995015ca.png"}],"result":"SUCCESS","precondition":false},{"number":13,"description":"Pablo select Tennis on Select para seleccionar deporte","duration":340,"startTime":"2022-11-23T16:08:26.823471400-05:00[America/Bogota]","screenshots":[{"screenshot":"f120b8e440d74990a68def1b2e2bdb06593743fc8a27bb76e9e1bb984532edaf.png"}],"result":"SUCCESS","precondition":false},{"number":14,"description":"Pablo select Tennis on Select para seleccionar segundo deporte","duration":303,"startTime":"2022-11-23T16:08:27.165687400-05:00[America/Bogota]","screenshots":[{"screenshot":"cadaa5f7de8fdffc58c3d5a30a1dc72868d695295b4b1f92d2228ccbbbcea5d0.png"}],"result":"SUCCESS","precondition":false},{"number":15,"description":"Pablo select Golf on Select para seleccionar segundo deporte","duration":261,"startTime":"2022-11-23T16:08:27.473816100-05:00[America/Bogota]","screenshots":[{"screenshot":"9259e1986658c5ff904e9d4c69be167befab629cf6b35c9d70390a2be63ed9d7.png"}],"result":"SUCCESS","precondition":false},{"number":16,"description":"Pablo enters \u0027http://tenis.com\u0027 into Input para el campo URL","duration":392,"startTime":"2022-11-23T16:08:27.737517-05:00[America/Bogota]","screenshots":[{"screenshot":"8a91b7c001badf59902c36c138f0b93a078b78fbf1bb5fec9dba4e3b742d7914.png"}],"result":"SUCCESS","precondition":false},{"number":17,"description":"Pablo enters \u0027tenis@tenis.com\u0027 into Input para el campo E-MAIL","duration":335,"startTime":"2022-11-23T16:08:28.135234700-05:00[America/Bogota]","screenshots":[{"screenshot":"e26b372c7a10eac2a542ef5dacf05bcdfa0f9d697f0d11326f3118e4fa4ad55a.png"}],"result":"SUCCESS","precondition":false},{"number":18,"description":"Pablo enters \u0027123\u0027 into Input para el campo Password","duration":348,"startTime":"2022-11-23T16:08:28.473204500-05:00[America/Bogota]","screenshots":[{"screenshot":"de70bced0df081e7db7f918968bced18d351a06831026ff4ddabd9939ba42ba9.png"}],"result":"SUCCESS","precondition":false},{"number":19,"description":"Pablo enters \u0027123\u0027 into Input para el campo Confirm Password","duration":374,"startTime":"2022-11-23T16:08:28.824104-05:00[America/Bogota]","screenshots":[{"screenshot":"5b56fcd812cf5c230a8f22124c3f151819196d2b7828ac6c98b88c734680123b.png"}],"result":"SUCCESS","precondition":false},{"number":20,"description":"Pablo enters \u0027123456\u0027 into Input para el campo MINIMUN FIELD SIZE","duration":355,"startTime":"2022-11-23T16:08:29.200141700-05:00[America/Bogota]","screenshots":[{"screenshot":"da0ab7bdd475fcd73710f3e0e69d97889e50035ce4659c0d86a63178ada37d7f.png"}],"result":"SUCCESS","precondition":false},{"number":21,"description":"Pablo enters \u0027123456\u0027 into Input para el campo MAXIMUN FIELD SIZE","duration":413,"startTime":"2022-11-23T16:08:29.558496600-05:00[America/Bogota]","screenshots":[{"screenshot":"7d0ad399d3b3369317092e10eaeffa3dae9b53a160c0e21b073ec4f987539795.png"}],"result":"SUCCESS","precondition":false},{"number":22,"description":"Pablo enters \u0027123\u0027 into Input para el campo NUMBER","duration":368,"startTime":"2022-11-23T16:08:29.973487400-05:00[America/Bogota]","screenshots":[{"screenshot":"9172ee9cdf79fef4293b56fc81259f006f30dc4a671629eaa0dfc59d6762b48d.png"}],"result":"SUCCESS","precondition":false},{"number":23,"description":"Pablo enters \u0027192.168.3.1\u0027 into Input para el campo IP","duration":394,"startTime":"2022-11-23T16:08:30.347670300-05:00[America/Bogota]","screenshots":[{"screenshot":"14b053f3f433e5f811de06f113b722a6de5052ff18e54670ef06ed1ec9aafd23.png"}],"result":"SUCCESS","precondition":false},{"number":24,"description":"Pablo enters \u00272011-12-01\u0027 into Input para el campo DATE","duration":347,"startTime":"2022-11-23T16:08:30.744040-05:00[America/Bogota]","screenshots":[{"screenshot":"c887ff3fba800f2dab2a62235cffc0229b773e834f7b2060d9207200dadd610e.png"}],"result":"SUCCESS","precondition":false},{"number":25,"description":"Pablo enters \u00272011-12-01\u0027 into Input para el campo DATE EARLIER","duration":379,"startTime":"2022-11-23T16:08:31.093488300-05:00[America/Bogota]","screenshots":[{"screenshot":"67b916d44b0585953775dd1bf03bf7c3463647cf6a0d33558784b33b70b773ec.png"}],"result":"SUCCESS","precondition":false},{"number":26,"description":"Pablo clicks on Botón de VALIDATE","duration":799,"startTime":"2022-11-23T16:08:31.476577800-05:00[America/Bogota]","screenshots":[{"screenshot":"596a8acdee4fbd19db31aee87cab9aef2c8f86d24d495ed1470609823fea4753.png"}],"result":"SUCCESS","precondition":false}]},{"number":27,"description":"Then Verifico ingreso exitoso","duration":10533,"startTime":"2022-11-23T16:08:32.453112800-05:00[America/Bogota]","screenshots":[{"screenshot":"596a8acdee4fbd19db31aee87cab9aef2c8f86d24d495ed1470609823fea4753.png"}],"result":"SUCCESS","precondition":false,"children":[{"number":28,"description":"Then Validar Exitencia de Popup should be (false)","duration":10421,"startTime":"2022-11-23T16:08:32.454113300-05:00[America/Bogota]","screenshots":[{"screenshot":"596a8acdee4fbd19db31aee87cab9aef2c8f86d24d495ed1470609823fea4753.png"}],"result":"SUCCESS","precondition":false,"children":[{"number":29,"description":"Then Popup de validaci\u0026oacute;n sobre cada campo should be an element that is not visible","duration":10249,"startTime":"2022-11-23T16:08:32.470120200-05:00[America/Bogota]","screenshots":[{"screenshot":"596a8acdee4fbd19db31aee87cab9aef2c8f86d24d495ed1470609823fea4753.png"}],"result":"SUCCESS","precondition":false}]}]}],"userStory":{"id":"formulario-popup-validation","storyName":"Formulario Popup Validation","path":"src/test/resources/features/demo.feature","narrative":"  El usuario debe poder ingresar al formulario los datos requeridos.\n  Cada campo del formulario realiza validaciones de obligatoriedad,\n  longitud y formato, el sistema debe presentar las validaciones respectivas\n  para cada campo a través un globo informativo.","type":"feature"},"featureTag":{"name":"Features/Formulario Popup Validation","type":"feature"},"title":"Digiligenciamiento exitoso del formulario Popup Validation","description":"  no se presenta ningún mensaje de validación.","tags":[{"name":"Formulario popup validation","type":"feature"},{"name":"Regresion","type":"tag"},{"name":"CasoExitoso","type":"tag"}],"startTime":"2022-11-23T16:08:04.357718100-05:00[America/Bogota]","duration":38692,"projectKey":"","sessionId":"16c0f258d5fee9a1c409273fce5d6ac2","driver":"chrome:pablo","manual":false,"testSource":"Cucumber","result":"SUCCESS"}